neuralart/__init__.py
neuralart/__main__.py
neuralart/neuralart.py
neuralart/version.txt
neuralart-1.1.1.data/scripts/neuralart
neuralart-1.1.1.dist-info/LICENSE
neuralart-1.1.1.dist-info/METADATA
neuralart-1.1.1.dist-info/WHEEL
neuralart-1.1.1.dist-info/top_level.txt
neuralart-1.1.1.dist-info/RECORD
