Metadata-Version: 2.1
Name: neuralart
Version: 1.1.1
Summary: A library for rendering generative art from a randomly initialized neural network.
Home-page: https://github.com/dstein64/neuralart
Author: Daniel Steinberg
Author-email: ds@dannyadam.com
License: MIT
Keywords: neural-networks,generative-art
Platform: UNKNOWN
Classifier: Development Status :: 4 - Beta
Classifier: Intended Audience :: Developers
Classifier: Topic :: Artistic Software
Classifier: License :: OSI Approved :: MIT License
Classifier: Operating System :: Unix
Classifier: Operating System :: POSIX :: Linux
Classifier: Operating System :: MacOS
Classifier: Operating System :: Microsoft :: Windows
Classifier: Programming Language :: Python :: 3
License-File: LICENSE
Requires-Dist: numpy
Requires-Dist: pillow
Requires-Dist: torch
